{
  "analysis": {
    "analysis_date": "May 09, 2026",
    "analysis_time": "20:34",
    "executive_summary": {
      "key_highlights": [
        "S&P 500 extends winning streak to 6 weeks, hitting fresh record on strong jobs report and Iran deal hopes.",
        "US added 115,000 jobs in April, beating expectations despite Iran war impact.",
        "Iran war is draining global oil buffer at unprecedented pace, with risk of $5 gasoline and DOJ investigating suspicious oil trades.",
        "Jim Cramer bullish on IBM, Goldman Sachs, Meta, Arista Networks, Taiwan Semi, and GE Vernova; cautious on AMD, Domino's, and Extreme Networks.",
        "Gold output falls in China as investor demand for bars and coins jumps, while Cramer is not bullish on gold.",
        "Inflation drumbeat persists for US consumer, with Fed cuts delayed to December according to Goldman.",
        "Trump planning to fire FDA Commissioner Marty Makary, adding regulatory uncertainty.",
        "Capital One earnings miss raises questions about consumer health; housing market showing signs of leveling out.",
        "China's energy imports plunge as Hormuz shipments choked; Beijing pushes AI data centers to adopt green energy.",
        "Crypto industry throws lap-dance party in bear market; Trump Media reports $2.2B in assets with crypto holdings driving Q1 loss."
      ],
      "market_sentiment_score": 75,
      "overall_sentiment": "positive",
      "headline_sources": [
        1,
        2,
        4,
        6,
        7,
        8,
        9,
        10,
        11,
        13,
        16,
        17,
        18,
        19,
        20,
        24,
        25,
        26,
        27,
        28,
        29,
        30,
        32,
        34,
        35,
        36,
        37,
        38,
        39,
        41,
        42,
        44,
        45,
        46,
        48,
        52,
        55,
        56,
        57,
        58,
        59,
        60,
        61,
        62,
        63,
        64,
        65,
        66,
        68,
        71,
        72,
        73,
        74,
        76,
        77,
        78,
        79,
        80,
        81,
        82,
        83,
        84,
        85,
        86,
        87,
        88,
        89,
        90,
        91,
        92,
        93,
        94,
        95,
        96,
        98,
        99,
        100
      ]
    },
    "market_insights": {
      "sectors": [
        {
          "sector": "Technology",
          "trend": "Strong earnings and AI-driven growth continue to fuel record runs for Nvidia, Taiwan Semi, and others, but software sector faces headwinds with market hating software (Salesforce). Cloudflare cuts jobs amid AI layoffs. Apple and Intel reach preliminary chip-making agreement. Quantinuum files for IPO.",
          "implications": "AI and semiconductor demand remains robust, but software stocks may underperform. Investors should favor hardware and AI infrastructure plays over pure software names in the near term.",
          "headline_sources": [
            13,
            15,
            29,
            32,
            35,
            36,
            37,
            63,
            64,
            65,
            68,
            72,
            73,
            85,
            86,
            87,
            91,
            96,
            100
          ]
        },
        {
          "sector": "Energy & Commodities",
          "trend": "Iran war is draining world's oil buffer at unprecedented pace, driving oil prices higher and risk of $5 gasoline. China's energy imports plunge. DOJ investigating suspicious oil trades. Gold output falls in China but investor demand for bars and coins jumps. Cramer not bullish on gold.",
          "implications": "Energy sector benefits from supply disruption, but geopolitical risk is elevated. Gold may see safe-haven demand but Cramer's caution suggests limited upside. Oil-related trades face regulatory scrutiny.",
          "headline_sources": [
            4,
            10,
            16,
            22,
            27,
            28,
            41,
            66,
            81,
            84,
            88,
            90,
            93
          ]
        },
        {
          "sector": "Financials",
          "trend": "Goldman Sachs expected to go higher per Cramer. Capital One earnings miss raises consumer health concerns. Fed cuts delayed to December. Mortgage rates moving back up. HELOC and home equity loan rates rising, equity-rich homeowners falling. Apollo CEO warns of 35% chance of major market shock.",
          "implications": "Financials may benefit from higher rates but consumer weakness is a risk. Mortgage and housing-related stocks face headwinds. Diversification and defensive positioning recommended.",
          "headline_sources": [
            26,
            30,
            38,
            46,
            52,
            55,
            58,
            62,
            95
          ]
        },
        {
          "sector": "Healthcare",
          "trend": "Becton Dickinson shows excellent execution. Thermo Fisher considered buyable. CVS argued as cheaper. Trump planning to fire FDA Commissioner, adding regulatory uncertainty. Health officials downplay pandemic risk from cruise hantavirus outbreak.",
          "implications": "Healthcare offers defensive qualities with select opportunities in medtech and pharma. Regulatory risk from FDA leadership change could create volatility.",
          "headline_sources": [
            7,
            11,
            54,
            56,
            100
          ]
        },
        {
          "sector": "Consumer & Retail",
          "trend": "Consumer under pressure from inflation and rising rates. Domino's not a buy yet. Kraft Heinz rallies after better-than-expected earnings. Expedia and Airbnb active in acquisitions. Spirit Airlines folded, one man's viral plan to revive it. Blind box trend gaining traction.",
          "implications": "Consumer discretionary stocks face headwinds from inflation and rate hikes. Select value plays like Kraft Heinz may offer upside. Travel and leisure remain mixed.",
          "headline_sources": [
            6,
            17,
            26,
            33,
            42,
            60,
            61,
            67
          ]
        },
        {
          "sector": "Real Estate & Housing",
          "trend": "Housing market leveling out as interest rate hikes pressure buyers. Mortgage rates move back up. Number of equity-rich homeowners falls. Warren Buffett sends blunt message on mortgages. HELOC rates rising.",
          "implications": "Housing sector faces continued pressure from higher rates. Homebuilders and mortgage lenders may underperform. Rent and commuting costs shifting location decisions.",
          "headline_sources": [
            6,
            38,
            43,
            52,
            58,
            62
          ]
        },
        {
          "sector": "Geopolitical & Macro",
          "trend": "Iran war dominates headlines: Hormuz clashes, ceasefire strained, UK moves warship, China summit stays on track despite concerns. France halts Middle East routes. Trump-Xi summit expected. China vows to defuse local government debt. Pakistan receives IMF tranche. New Zealanders moving to Australia in record numbers.",
          "implications": "Geopolitical risk is elevated, particularly in Middle East. Oil supply disruption and inflation are key concerns. Diplomacy (Trump-Xi, Iran ceasefire) could provide upside catalysts. China's debt efforts are positive for EM stability.",
          "headline_sources": [
            8,
            9,
            10,
            16,
            22,
            27,
            66,
            74,
            78,
            83,
            84,
            93,
            98
          ]
        }
      ],
      "key_themes": [
        "Iran war and oil supply disruption",
        "AI-driven tech rally and layoffs",
        "Inflation persistence and delayed Fed cuts",
        "Consumer health under pressure",
        "Housing market slowdown",
        "Regulatory uncertainty (FDA, DOJ, marijuana)",
        "Geopolitical tensions and summit diplomacy",
        "China's energy and debt challenges",
        "Crypto and alternative assets in bear market",
        "Record stock market rally despite risks"
      ],
      "headline_sources": [
        1,
        2,
        4,
        6,
        7,
        8,
        9,
        10,
        11,
        13,
        16,
        17,
        18,
        19,
        20,
        24,
        25,
        26,
        27,
        28,
        29,
        30,
        32,
        34,
        35,
        36,
        37,
        38,
        39,
        41,
        42,
        44,
        45,
        46,
        48,
        52,
        55,
        56,
        57,
        58,
        59,
        60,
        61,
        62,
        63,
        64,
        65,
        66,
        68,
        71,
        72,
        73,
        74,
        76,
        77,
        78,
        79,
        80,
        81,
        82,
        83,
        84,
        85,
        86,
        87,
        88,
        89,
        90,
        91,
        92,
        93,
        94,
        95,
        96,
        98,
        99,
        100
      ]
    },
    "risk_assessment": [
      {
        "risk_factor": "Iran war escalation and oil supply disruption",
        "impact": "High",
        "likelihood": "Medium",
        "mitigation": "Reduce exposure to oil-sensitive sectors, increase cash and short-duration bonds, consider hedging with energy stocks or commodities.",
        "headline_sources": [
          10,
          16,
          22,
          27,
          66,
          81,
          84,
          88,
          90,
          93
        ]
      },
      {
        "risk_factor": "Inflation persistence and delayed Fed cuts",
        "impact": "High",
        "likelihood": "High",
        "mitigation": "Favor value stocks, TIPS, and short-duration fixed income. Avoid long-duration bonds and growth stocks with high valuations.",
        "headline_sources": [
          17,
          44,
          46,
          59
        ]
      },
      {
        "risk_factor": "Consumer health deterioration",
        "impact": "Medium",
        "likelihood": "Medium",
        "mitigation": "Reduce exposure to consumer discretionary, focus on defensive sectors like healthcare and staples. Monitor credit card delinquencies and retail sales.",
        "headline_sources": [
          6,
          26,
          38,
          55,
          58,
          62
        ]
      },
      {
        "risk_factor": "Regulatory uncertainty (FDA, DOJ, marijuana)",
        "impact": "Medium",
        "likelihood": "Medium",
        "mitigation": "Avoid stocks with high regulatory exposure (pharma, cannabis, oil trading). Diversify across sectors with less regulatory risk.",
        "headline_sources": [
          11,
          28,
          80,
          88,
          90,
          94
        ]
      },
      {
        "risk_factor": "AI-driven market shock and layoffs",
        "impact": "Medium",
        "likelihood": "Low",
        "mitigation": "Maintain diversified tech exposure, avoid overconcentration in AI hype stocks. Consider quality names with strong fundamentals.",
        "headline_sources": [
          64,
          85,
          95
        ]
      },
      {
        "risk_factor": "Geopolitical tensions (Trump-Xi summit, China debt)",
        "impact": "Medium",
        "likelihood": "Medium",
        "mitigation": "Monitor summit outcomes for trade and tariff implications. China debt resolution could be positive for EM, but failure could trigger volatility.",
        "headline_sources": [
          8,
          78,
          83,
          98
        ]
      }
    ],
    "strategic_recommendations": {
      "opportunities": [
        {
          "recommendation": "Buy IBM on Cramer's bullish call and strong earnings momentum",
          "rationale": "IBM is benefiting from AI and hybrid cloud demand, with Cramer explicitly recommending it. Strong fundamentals and reasonable valuation.",
          "tickers": [
            "IBM"
          ],
          "timeframe": "medium-term",
          "headline_sources": [
            2
          ]
        },
        {
          "recommendation": "Buy Nvidia on AI expansion and record stock performance",
          "rationale": "Nvidia continues to lead AI chip demand, with Barron's reporting record highs. Strong revenue growth and margins.",
          "tickers": [
            "NVDA"
          ],
          "timeframe": "long-term",
          "headline_sources": [
            86
          ]
        },
        {
          "recommendation": "Buy Goldman Sachs on Cramer's bullish view and rate environment",
          "rationale": "Goldman Sachs is well-positioned for higher rates and investment banking recovery. Cramer sees it going higher.",
          "tickers": [
            "GS"
          ],
          "timeframe": "medium-term",
          "headline_sources": [
            30
          ]
        },
        {
          "recommendation": "Buy Meta on Cramer's 'stop worrying and start buying' call",
          "rationale": "Meta's advertising revenue and AI investments are driving growth. Valuation is attractive after recent pullback.",
          "tickers": [
            "META"
          ],
          "timeframe": "medium-term",
          "headline_sources": [
            87
          ]
        },
        {
          "recommendation": "Buy Taiwan Semi on massive business demand",
          "rationale": "TSMC has more business than it can handle, benefiting from AI and chip demand. Strong secular growth.",
          "tickers": [
            "TSM"
          ],
          "timeframe": "long-term",
          "headline_sources": [
            68
          ]
        },
        {
          "recommendation": "Buy GE Vernova on Cramer's suggestion",
          "rationale": "GE Vernova is a pure-play energy transition stock with strong fundamentals and Cramer's endorsement.",
          "tickers": [
            "GEV"
          ],
          "timeframe": "medium-term",
          "headline_sources": [
            48
          ]
        },
        {
          "recommendation": "Buy Arista Networks on Cramer's 'time to buy' call",
          "rationale": "Arista benefits from data center networking demand driven by AI. Strong earnings and growth outlook.",
          "tickers": [
            "ANET"
          ],
          "timeframe": "medium-term",
          "headline_sources": [
            37
          ]
        },
        {
          "recommendation": "Buy Rocket Lab on Stifel buy rating and stock surge",
          "rationale": "Rocket Lab is gaining traction in space launch and satellite services. Analyst upgrade and strong momentum.",
          "tickers": [
            "RKLB"
          ],
          "timeframe": "long-term",
          "headline_sources": [
            19
          ]
        },
        {
          "recommendation": "Buy high-yield savings and CDs at 4%+ APY for cash allocation",
          "rationale": "With rates still elevated, locking in 4%+ yields provides safe income while waiting for better entry points in equities.",
          "tickers": [],
          "timeframe": "short-term",
          "headline_sources": [
            1,
            25
          ]
        }
      ],
      "defensive_moves": [
        {
          "recommendation": "Reduce exposure to consumer discretionary and software stocks",
          "rationale": "Consumer health is cracking (Capital One miss, inflation) and software sector is hated by market. Shift to defensive sectors.",
          "tickers": [
            "XLP",
            "XLV",
            "XLU"
          ],
          "timeframe": "short-term",
          "headline_sources": [
            26,
            32,
            60
          ]
        },
        {
          "recommendation": "Hedge against oil price spike with energy stocks or commodities",
          "rationale": "Iran war is draining oil buffer, risk of $5 gasoline. Energy sector benefits from supply disruption.",
          "tickers": [
            "XLE",
            "USO",
            "CVX",
            "XOM"
          ],
          "timeframe": "short-term",
          "headline_sources": [
            16,
            81,
            84
          ]
        },
        {
          "recommendation": "Increase cash and short-duration bonds",
          "rationale": "Fed cuts delayed to December, rates remain high. Cash and short-term bonds offer attractive yields with low risk.",
          "tickers": [
            "SHY",
            "BIL",
            "SGOV"
          ],
          "timeframe": "short-term",
          "headline_sources": [
            46,
            95
          ]
        },
        {
          "recommendation": "Avoid gold despite safe-haven demand; Cramer not bullish",
          "rationale": "Cramer's caution on gold suggests limited upside despite geopolitical tensions. Better opportunities elsewhere.",
          "tickers": [
            "GLD",
            "IAU"
          ],
          "timeframe": "medium-term",
          "headline_sources": [
            41
          ]
        },
        {
          "recommendation": "Monitor DOJ investigation into oil trades; avoid speculative oil plays",
          "rationale": "Regulatory scrutiny could lead to volatility in oil futures and related stocks. Stick with large-cap energy.",
          "tickers": [],
          "timeframe": "short-term",
          "headline_sources": [
            28,
            88,
            90
          ]
        }
      ]
    },
    "market_outlook": {
      "short_term": "The market is riding a 6-week winning streak driven by strong earnings and hopes for Iran de-escalation. However, inflation persistence, delayed Fed cuts, and geopolitical risks (Iran war, Trump-Xi summit) could trigger volatility. Expect continued strength in AI/tech and energy, but caution on consumer and housing. S&P 500 may test new highs but faces resistance from rising rates and oil prices.",
      "long_term": "The long-term outlook is cautiously positive. AI and semiconductor demand will drive growth, but inflation and geopolitical tensions remain key risks. Fed cuts expected by December could provide a tailwind. Housing and consumer sectors may face prolonged pressure. China's debt resolution and green energy push are positive for global stability. Investors should maintain a balanced portfolio with defensive hedges.",
      "key_catalysts": [
        "Trump-Xi summit outcome (trade and tariff implications)",
        "Iran ceasefire negotiations and Hormuz shipping disruption",
        "Fed meeting minutes and inflation data (CPI, PCE)",
        "DOJ investigation results on oil trades",
        "FDA leadership change and regulatory impact",
        "China's local government debt resolution progress",
        "AI earnings from Nvidia, Meta, and other tech giants",
        "Consumer spending and retail sales data",
        "Oil price movements and gasoline prices",
        "Housing market data (home sales, prices, mortgage rates)"
      ],
      "watch_list": [
        "WTI and Brent crude oil prices",
        "10-year Treasury yield",
        "US Dollar Index (DXY)",
        "VIX volatility index",
        "S&P 500 and Nasdaq 100 levels",
        "Gold and silver prices",
        "Bitcoin and crypto market",
        "Jobless claims and employment data",
        "Consumer confidence and sentiment indices",
        "Earnings reports from key companies (Nvidia, Salesforce, etc.)"
      ],
      "headline_sources": [
        1,
        2,
        4,
        6,
        7,
        8,
        9,
        10,
        11,
        13,
        16,
        17,
        18,
        19,
        20,
        24,
        25,
        26,
        27,
        28,
        29,
        30,
        32,
        34,
        35,
        36,
        37,
        38,
        39,
        41,
        42,
        44,
        45,
        46,
        48,
        52,
        55,
        56,
        57,
        58,
        59,
        60,
        61,
        62,
        63,
        64,
        65,
        66,
        68,
        71,
        72,
        73,
        74,
        76,
        77,
        78,
        79,
        80,
        81,
        82,
        83,
        84,
        85,
        86,
        87,
        88,
        89,
        90,
        91,
        92,
        93,
        94,
        95,
        96,
        98,
        99,
        100
      ]
    }
  },
  "headlines": [
    {
      "index": 1,
      "headline": "Best high-yield savings interest rates today, May 9, 2026 (Earn up to 4.1% APY)",
      "url": "https://finance.yahoo.com/personal-finance/banking/article/best-high-yield-savings-interest-rates-today-saturday-may-9-2026-100000422.html",
      "publishedAt": "2026-05-09T10:00:00Z"
    },
    {
      "index": 2,
      "headline": "Jim Cramer Says “I Want You to Buy IBM”",
      "url": "https://finance.yahoo.com/markets/stocks/articles/jim-cramer-says-want-buy-183624182.html",
      "publishedAt": "2026-05-09T18:36:24Z"
    },
    {
      "index": 3,
      "headline": "Ryan Serhant Helps Boston Mom Find New Home For Her Family",
      "url": "https://www.today.com/video/ryan-serhant-helps-a-single-mom-find-new-home-in-boston-262914629988",
      "publishedAt": "2026-05-07T15:11:08+00:00"
    },
    {
      "index": 4,
      "headline": "China Gold Output Falls as Investor Demand for Bars, Coins Jumps",
      "url": "https://www.bloomberg.com/news/articles/2026-05-09/china-gold-output-falls-as-investor-demand-for-bars-coins-jumps",
      "publishedAt": "2026-05-09T03:32:54+00:00"
    },
    {
      "index": 5,
      "headline": "Compass Minerals International Q2 Earnings Call Highlights",
      "url": "https://finance.yahoo.com/markets/stocks/articles/compass-minerals-international-q2-earnings-200430608.html",
      "publishedAt": "2026-05-09T20:04:30Z"
    },
    {
      "index": 6,
      "headline": "Some commuters now pay $1,600 a month just to get to work — how the cost of gas is changing the math on where you live",
      "url": "https://finance.yahoo.com/economy/articles/commuters-now-pay-1-600-181000608.html",
      "publishedAt": "2026-05-09T18:10:00Z"
    },
    {
      "index": 7,
      "headline": "Jim Cramer on Becton, Dickinson: “The Company Showed Excellent Execution Across the Board”",
      "url": "https://finance.yahoo.com/markets/stocks/articles/jim-cramer-becton-dickinson-company-183633038.html",
      "publishedAt": "2026-05-09T18:36:33Z"
    },
    {
      "index": 8,
      "headline": "‘It’s Not Because They Want to Be Friends’: Brilliant on What to Expect From the Trump-Xi Summit",
      "url": "https://www.bloomberg.com/news/videos/2026-05-09/what-to-expect-from-the-trump-xi-summit-video",
      "publishedAt": "2026-05-09T12:04:23+00:00"
    },
    {
      "index": 9,
      "headline": "France Halts Middle East Routes Again Into May 2026 Amid Security Crisis",
      "url": "https://www.nomadlawyer.org/france-halts-middle-east-routes-may-2026",
      "publishedAt": "2026-05-09T08:16:04Z"
    },
    {
      "index": 10,
      "headline": "US Awaits Iranian Response After Hormuz Clashes Strain Ceasefire",
      "url": "https://www.bloomberg.com/news/videos/2026-05-09/us-awaits-response-after-hormuz-clashes-strain-ceasefire-video",
      "publishedAt": "2026-05-09T14:00:29+00:00"
    },
    {
      "index": 11,
      "headline": "Trump Is Planning to Fire FDA Commissioner Marty Makary - WSJ",
      "url": "https://www.wsj.com/health/healthcare/trump-planning-to-fire-fda-commissioner-marty-makary-34c072e2",
      "publishedAt": "2026-05-08T17:09:00Z"
    },
    {
      "index": 12,
      "headline": "Compass Diversified Q1 Earnings Call Highlights",
      "url": "https://finance.yahoo.com/markets/stocks/articles/compass-diversified-q1-earnings-call-200431109.html",
      "publishedAt": "2026-05-09T20:04:31Z"
    },
    {
      "index": 13,
      "headline": "Jim Cramer on Palantir: “Great Margins, Terrific Revenue Growth”",
      "url": "https://finance.yahoo.com/markets/stocks/articles/jim-cramer-palantir-great-margins-183629785.html",
      "publishedAt": "2026-05-09T18:36:29Z"
    },
    {
      "index": 14,
      "headline": "What's a Blind Box and Why Are Big Brands Following the Trend?",
      "url": "https://www.today.com/video/what-s-a-blind-box-and-why-are-big-brands-following-the-trend-262987845731",
      "publishedAt": "2026-05-08T13:35:34+00:00"
    },
    {
      "index": 15,
      "headline": "Jim Cramer on Extreme Networks: “I Don’t Recommend Stocks Like This”",
      "url": "https://finance.yahoo.com/markets/stocks/articles/jim-cramer-extreme-networks-don-183647207.html",
      "publishedAt": "2026-05-09T18:36:47Z"
    },
    {
      "index": 16,
      "headline": "Iran War Is Draining World’s Oil Buffer at an Unprecedented Pace",
      "url": "https://www.bloomberg.com/news/articles/2026-05-09/iran-war-is-draining-world-s-oil-buffer-at-unprecedented-pace",
      "publishedAt": "2026-05-09T12:30:00+00:00"
    },
    {
      "index": 17,
      "headline": "Inflation Drumbeat Persists for Unnerved US Consumer",
      "url": "https://www.bloomberg.com/news/articles/2026-05-09/inflation-drumbeat-persists-for-unnerved-us-consumer",
      "publishedAt": "2026-05-09T20:00:00+00:00"
    },
    {
      "index": 18,
      "headline": "Even Investors Trying to Avoid the SpaceX IPO May Have No Choice but to Eventually Own the Stock",
      "url": "https://www.fool.com/investing/2026/05/09/even-investors-trying-to-avoid-the-spacex-ipo-may/",
      "publishedAt": "2026-05-09T08:08:03Z"
    },
    {
      "index": 19,
      "headline": "Why Rocket Lab (RKLB) Stock Blasted Higher Today and Why Stifel Thinks It Is a Buy - TipRanks",
      "url": "https://www.tipranks.com/news/article/why-rocket-lab-rklb-stock-blasted-higher-today-and-why-stifel-thinks-it-is-still-a-buy",
      "publishedAt": "2026-05-08T17:20:50Z"
    },
    {
      "index": 20,
      "headline": "Canadian Natural Resources Q1 Earnings Call Highlights",
      "url": "https://finance.yahoo.com/sectors/energy/articles/canadian-natural-resources-q1-earnings-200430874.html",
      "publishedAt": "2026-05-09T20:04:30Z"
    },
    {
      "index": 21,
      "headline": "Ted Turner managed one Braves game — and forever changed professional sports",
      "url": "https://www.nbcnews.com/sports/baseball/ted-turner-managed-one-braves-game-forever-changed-professional-sports-rcna343897",
      "publishedAt": "2026-05-06T23:22:15+00:00"
    },
    {
      "index": 22,
      "headline": "Iran War Drives Africa’s Fertilizer Crisis",
      "url": "https://www.bloomberg.com/news/videos/2026-05-09/iran-war-drives-africa-s-fertilizer-crisis",
      "publishedAt": "2026-05-09T05:00:13+00:00"
    },
    {
      "index": 23,
      "headline": "Moving people and money across borders",
      "url": "https://www.bloomberg.com/news/newsletters/2026-05-09/moving-people-and-money-across-borders",
      "publishedAt": "2026-05-09T12:00:00+00:00"
    },
    {
      "index": 24,
      "headline": "Trump Media Reports $2.2B in Assets as Crypto Holdings Drive Q1 Loss",
      "url": "https://finance.yahoo.com/markets/crypto/articles/trump-media-reports-2-2b-170800533.html",
      "publishedAt": "2026-05-09T17:08:00Z"
    },
    {
      "index": 25,
      "headline": "Best CD rates today, Saturday, May 9, 2026 (best account provides 4% APY)",
      "url": "https://finance.yahoo.com/personal-finance/banking/article/best-cd-rates-today-saturday-may-9-2026-100000061.html",
      "publishedAt": "2026-05-09T10:00:00Z"
    },
    {
      "index": 26,
      "headline": "Capital One's Earnings Miss Raises a Bigger Question: Is the Consumer Finally Cracking?",
      "url": "https://finance.yahoo.com/markets/stocks/articles/capital-ones-earnings-miss-raises-195000597.html",
      "publishedAt": "2026-05-09T19:50:00Z"
    },
    {
      "index": 27,
      "headline": "U.S. added 115,000 jobs in April as economy contends with Iran war impact",
      "url": "https://www.nbcnews.com/business/economy/april-jobs-report-iran-war-pressure-rcna344166",
      "publishedAt": "2026-05-08T09:00:41+00:00"
    },
    {
      "index": 28,
      "headline": "Source: DOJ investigating suspicious oil trades timed around Iran war",
      "url": "https://www.nbcnews.com/video/source-doj-investigating-suspicious-oil-trades-timed-around-iran-war-262944837880",
      "publishedAt": "2026-05-07T21:51:05+00:00"
    },
    {
      "index": 29,
      "headline": "Jim Cramer Slams AMD Downgrade",
      "url": "https://finance.yahoo.com/markets/stocks/articles/jim-cramer-slams-amd-downgrade-183636901.html",
      "publishedAt": "2026-05-09T18:36:36Z"
    },
    {
      "index": 30,
      "headline": "Jim Cramer on Goldman Sachs: “I Think That It’s Going Higher”",
      "url": "https://finance.yahoo.com/markets/stocks/articles/jim-cramer-goldman-sachs-think-183644730.html",
      "publishedAt": "2026-05-09T18:36:44Z"
    },
    {
      "index": 31,
      "headline": "Rachel Entrekin Shatters 250-Mile Course Record",
      "url": "https://www.bloomberg.com/news/videos/2026-05-09/rachel-entrekin-shatters-250-mile-course-record-video",
      "publishedAt": "2026-05-09T17:19:32+00:00"
    },
    {
      "index": 32,
      "headline": "Jim Cramer on Salesforce: “It’s Tough Because the Market Hates Software”",
      "url": "https://finance.yahoo.com/markets/stocks/articles/jim-cramer-salesforce-tough-because-183638905.html",
      "publishedAt": "2026-05-09T18:36:38Z"
    },
    {
      "index": 33,
      "headline": "When Spirit folded, this tiny airport suddenly had zero flights - The Washington Post",
      "url": "https://www.washingtonpost.com/nation/2026/05/08/spirit-shutdown-bankrupt-airport/",
      "publishedAt": "2026-05-08T16:00:40Z"
    },
    {
      "index": 34,
      "headline": "AMETEK Bets $5 Billion on Indicor Deal to Boost Industrial Tech Portfolio",
      "url": "https://finance.yahoo.com/markets/stocks/articles/ametek-bets-5-billion-indicor-200432724.html",
      "publishedAt": "2026-05-09T20:04:32Z"
    },
    {
      "index": 35,
      "headline": "Beijing pushes AI data centres to adopt green energy under action plan",
      "url": "https://www.scmp.com/tech/tech-trends/article/3352983/beijing-pushes-ai-data-centres-adopt-green-energy-under-action-plan",
      "publishedAt": "2026-05-09T08:06:24Z"
    },
    {
      "index": 36,
      "headline": "Jim Cramer on Shopify: “You Want to Buy It When the Stock’s Ice Cold”",
      "url": "https://finance.yahoo.com/markets/stocks/articles/jim-cramer-shopify-want-buy-184754746.html",
      "publishedAt": "2026-05-09T18:47:54Z"
    },
    {
      "index": 37,
      "headline": "Jim Cramer on Arista Networks: “Time to Buy”",
      "url": "https://finance.yahoo.com/markets/stocks/articles/jim-cramer-arista-networks-time-184752029.html",
      "publishedAt": "2026-05-09T18:47:52Z"
    },
    {
      "index": 38,
      "headline": "HELOC and home equity loan rates Saturday, May 9, 2026: Number of 'equity-rich' homeowners falls",
      "url": "https://finance.yahoo.com/personal-finance/mortgages/article/heloc-home-equity-loan-interest-rates-today-saturday-may-9-2026-100000312.html",
      "publishedAt": "2026-05-09T10:00:00Z"
    },
    {
      "index": 39,
      "headline": "S&P 500 extends winning streak to 6 weeks. What drove the stock market gains",
      "url": "https://www.cnbc.com/2026/05/09/sp-500-extends-winning-streak-to-6-weeks-what-drove-the-stock-market-gains.html",
      "publishedAt": "2026-05-09T20:15:25.000000Z"
    },
    {
      "index": 40,
      "headline": "Power Integrations, Inc. (POWI) Q1 2026 Earnings Call Transcript",
      "url": "https://seekingalpha.com/article/4901906-power-integrations-inc-powi-q1-2026-earnings-call-transcript",
      "publishedAt": "2026-05-09T08:11:14Z"
    },
    {
      "index": 41,
      "headline": "Jim Cramer Calls Agnico Eagle the “Best One” But Is Not Bullish on Gold",
      "url": "https://finance.yahoo.com/markets/stocks/articles/jim-cramer-calls-agnico-eagle-183632048.html",
      "publishedAt": "2026-05-09T18:36:32Z"
    },
    {
      "index": 42,
      "headline": "Expedia Spent $279 Million on Acquisitions in Q1, Airbnb Gained $70 Million on Tiqets Deal: Scoop",
      "url": "https://finance.yahoo.com/markets/stocks/articles/expedia-spent-279-million-acquisitions-192926831.html",
      "publishedAt": "2026-05-09T19:29:26Z"
    },
    {
      "index": 43,
      "headline": "7NEWS The Issue Podcast: Mortgage change that could save you $11,000 in two years as interest rates rise again",
      "url": "https://7news.com.au/news/7news-the-issue-podcast-mortgage-change-that-could-save-you-11000-in-two-years-as-interest-rates-rise-again-c-22259596",
      "publishedAt": "2026-05-09T08:06:00Z"
    },
    {
      "index": 44,
      "headline": "Lagarde Says ECB Torn Between Risk of Acting Too Early, Too Late",
      "url": "https://www.bloomberg.com/news/articles/2026-05-09/lagarde-says-ecb-torn-between-risk-of-acting-too-early-too-late",
      "publishedAt": "2026-05-09T08:41:10+00:00"
    },
    {
      "index": 45,
      "headline": "Earnings Bonanza That No One Saw Coming Fuels Stocks’ Record Run",
      "url": "https://www.bloomberg.com/news/articles/2026-05-09/earnings-bonanza-that-no-one-saw-coming-fuels-stocks-record-run",
      "publishedAt": "2026-05-09T13:00:00+00:00"
    },
    {
      "index": 46,
      "headline": "Goldman Sees Fed Cuts Delayed to December, March on Inflation",
      "url": "https://www.bloomberg.com/news/articles/2026-05-09/goldman-sees-fed-cuts-delayed-to-december-march-on-inflation",
      "publishedAt": "2026-05-09T06:24:55+00:00"
    },
    {
      "index": 47,
      "headline": "UK airport to stop ALL flights from today before shutting for good after 90 years",
      "url": "https://www.thesun.co.uk/travel/39056623/coventry-airport-stops-flights-closing/",
      "publishedAt": "2026-05-09T08:32:00Z"
    },
    {
      "index": 48,
      "headline": "Jim Cramer Suggests “Might Want to Get Some GE Vernova”",
      "url": "https://finance.yahoo.com/markets/stocks/articles/jim-cramer-suggests-might-want-183622001.html",
      "publishedAt": "2026-05-09T18:36:22Z"
    },
    {
      "index": 49,
      "headline": "Songwe Sesame Farmers Harvest Massive TZS 3 Billion Windfall in Digital Auction",
      "url": "https://streamlinefeed.co.ke/news/songwe-sesame-farmers-harvest-massive-tzs-3-billion-windfall-in-digital-auction",
      "publishedAt": "2026-05-09T08:04:20Z"
    },
    {
      "index": 50,
      "headline": "Exploring The Met's New \"Costume Art\" Exhibit",
      "url": "https://www.bloomberg.com/news/videos/2026-05-09/exploring-the-met-s-new-costume-art-exhibit-video",
      "publishedAt": "2026-05-09T16:18:17+00:00"
    },
    {
      "index": 51,
      "headline": "Bloomberg This Weekend 5/9/2026",
      "url": "https://www.bloomberg.com/news/videos/2026-05-09/bloomberg-this-weekend-5-9-2026-video",
      "publishedAt": "2026-05-09T17:35:00+00:00"
    },
    {
      "index": 52,
      "headline": "Warren Buffett sends blunt message on mortgages, home financing",
      "url": "https://finance.yahoo.com/markets/options/articles/warren-buffett-sends-blunt-message-140700722.html",
      "publishedAt": "2026-05-08T14:07:00Z"
    },
    {
      "index": 53,
      "headline": "Wall Street Week | High Stakes Summit, New Zealand's Brain Drain, Stablecoin Adoption, Bubbly Water",
      "url": "https://www.bloomberg.com/news/videos/2026-05-08/wall-street-week-high-stakes-summit-talent-troubles-video",
      "publishedAt": "2026-05-08T23:14:55+00:00"
    },
    {
      "index": 54,
      "headline": "Health Officials Downplay Pandemic Risk From Cruise Hantavirus Outbreak",
      "url": "https://www.bloomberg.com/news/videos/2026-05-09/health-officials-downplay-risk-from-hantavirus-outbreak-video",
      "publishedAt": "2026-05-09T17:09:07+00:00"
    },
    {
      "index": 55,
      "headline": "Claros Mortgage Trust Q1 Earnings Call Highlights",
      "url": "https://finance.yahoo.com/markets/stocks/articles/claros-mortgage-trust-q1-earnings-200430455.html",
      "publishedAt": "2026-05-09T20:04:30Z"
    },
    {
      "index": 56,
      "headline": "Jim Cramer on CVS: “I Would Argue That It’s Cheaper”",
      "url": "https://finance.yahoo.com/markets/stocks/articles/jim-cramer-cvs-argue-cheaper-183640995.html",
      "publishedAt": "2026-05-09T18:36:40Z"
    },
    {
      "index": 57,
      "headline": "Why New Zealanders Are Moving To Australia in Record Numbers",
      "url": "https://www.bloomberg.com/news/videos/2026-05-09/why-new-zealanders-are-moving-to-australia-video",
      "publishedAt": "2026-05-09T14:03:53+00:00"
    },
    {
      "index": 58,
      "headline": "Housing market 'levelling out' as interest rate hikes place pressure on buyers",
      "url": "https://www.abc.net.au/news/2026-05-09/housing-market-steady-amid-buyer-uncertainty/106661662",
      "publishedAt": "2026-05-09T08:14:51Z"
    },
    {
      "index": 59,
      "headline": "Colombia Inflation Ticks Up, Fueling Case For Renewed Rate Hikes",
      "url": "https://www.bloomberg.com/news/articles/2026-05-08/colombia-inflation-ticks-up-fueling-case-for-renewed-rate-hikes",
      "publishedAt": "2026-05-08T23:30:57+00:00"
    },
    {
      "index": 60,
      "headline": "Jim Cramer on Domino’s Pizza: “We’re Not Going to Buy It Yet”",
      "url": "https://finance.yahoo.com/markets/stocks/articles/jim-cramer-domino-pizza-not-183630814.html",
      "publishedAt": "2026-05-09T18:36:30Z"
    },
    {
      "index": 61,
      "headline": "Jim Cramer Discusses Kraft Heinz Rally After Better Than Expected Earnings",
      "url": "https://finance.yahoo.com/markets/stocks/articles/jim-cramer-discusses-kraft-heinz-183641577.html",
      "publishedAt": "2026-05-09T18:36:41Z"
    },
    {
      "index": 62,
      "headline": "Mortgage and refinance interest rates today, May 9, 2026: 30- and 15-year rates move back up",
      "url": "https://finance.yahoo.com/personal-finance/mortgages/article/mortgage-refinance-interest-rates-today-saturday-may-9-2026-100000903.html",
      "publishedAt": "2026-05-09T10:00:00Z"
    },
    {
      "index": 63,
      "headline": "Honeywell-Backed Computing Firm Quantinuum Files for US IPO",
      "url": "https://www.bloomberg.com/news/articles/2026-05-08/honeywell-backed-computing-firm-quantinuum-files-for-us-ipo",
      "publishedAt": "2026-05-08T20:22:44+00:00"
    },
    {
      "index": 64,
      "headline": "'A good scapegoat': Wall Street assesses latest AI-linked job cuts",
      "url": "https://finance.yahoo.com/markets/article/a-good-scapegoat-wall-street-assesses-latest-ai-linked-job-cuts-170836684.html",
      "publishedAt": "2026-05-09T17:08:36Z"
    },
    {
      "index": 65,
      "headline": "Jim Cramer Highlights Stocks Like Sandisk Are “Making You So Much Money”",
      "url": "https://finance.yahoo.com/markets/stocks/articles/jim-cramer-highlights-stocks-sandisk-183621371.html",
      "publishedAt": "2026-05-09T18:36:21Z"
    },
    {
      "index": 66,
      "headline": "Air India to Cut Costs, Reduce Flights as War Worsens Financial Struggles",
      "url": "https://www.bloomberg.com/news/articles/2026-05-08/air-india-to-cut-costs-reduce-flights-as-war-worsens-financial-struggles",
      "publishedAt": "2026-05-08T06:18:04+00:00"
    },
    {
      "index": 67,
      "headline": "‘Get in loser, we’re buying Spirit’: One man’s viral plan to revive the airline",
      "url": "https://www.nbcnews.com/news/us-news/get-losers-re-buying-airline-spirit-revival-plan-going-viral-rcna343953",
      "publishedAt": "2026-05-09T14:00:42+00:00"
    },
    {
      "index": 68,
      "headline": "Jim Cramer on Taiwan Semi: “They Have More Business Than They Can Handle”",
      "url": "https://finance.yahoo.com/markets/stocks/articles/jim-cramer-taiwan-semi-more-183646491.html",
      "publishedAt": "2026-05-09T18:36:46Z"
    },
    {
      "index": 69,
      "headline": "Royal Mail issues delivery disruption alert for 20 UK postcodes this weekend - full list",
      "url": "https://www.mirror.co.uk/money/household-bills/royal-mail-delays-this-weekend-37132877",
      "publishedAt": "2026-05-09T08:27:00Z"
    },
    {
      "index": 70,
      "headline": "Is your savings account interest rate as good as you think it is?",
      "url": "https://www.1news.co.nz/2026/05/09/is-your-savings-account-interest-rate-as-good-as-you-think-it-is/",
      "publishedAt": "2026-05-09T08:06:39Z"
    },
    {
      "index": 71,
      "headline": "Crypto Industry Throws Lap-Dance Party in Middle of Bear Market",
      "url": "https://www.bloomberg.com/news/articles/2026-05-09/crypto-industry-throws-lap-dance-party-in-middle-of-bear-market",
      "publishedAt": "2026-05-09T12:00:00+00:00"
    },
    {
      "index": 72,
      "headline": "Jim Cramer on Corning: “The Company’s More Relevant Than Ever”",
      "url": "https://finance.yahoo.com/markets/stocks/articles/jim-cramer-corning-company-more-183626304.html",
      "publishedAt": "2026-05-09T18:36:26Z"
    },
    {
      "index": 73,
      "headline": "Jim Cramer Says “I Wish I’d Bought Dell for My Charitable Trust a Hundred Points Ago”",
      "url": "https://finance.yahoo.com/markets/stocks/articles/jim-cramer-says-wish-d-184751465.html",
      "publishedAt": "2026-05-09T18:47:51Z"
    },
    {
      "index": 74,
      "headline": "Pakistan to Receive $1.32 Billion as IMF Board Approves Tranches",
      "url": "https://www.bloomberg.com/news/articles/2026-05-08/pakistan-to-receive-1-32-billion-as-imf-board-approves-tranches",
      "publishedAt": "2026-05-08T22:21:46+00:00"
    },
    {
      "index": 75,
      "headline": "I found a framed stock certificate in my late father’s things. How do I find out if it’s worth anything?",
      "url": "https://finance.yahoo.com/markets/stocks/articles/found-framed-stock-certificate-father-191500804.html",
      "publishedAt": "2026-05-09T19:15:00Z"
    },
    {
      "index": 76,
      "headline": "S&P 500 rises to fresh record on strong jobs report and Iran deal hopes, heads for 6th winning week in a row: Live updates - CNBC",
      "url": "https://www.cnbc.com/2026/05/07/stock-market-today-live-updates.html",
      "publishedAt": "2026-05-08T15:24:00Z"
    },
    {
      "index": 77,
      "headline": "Galaxy S23 Ultra Users: New Samsung Update Shows It’s Time To Sell",
      "url": "https://www.forbes.com/sites/jaymcgregor/2026/05/09/samsung-galaxy-s23-ultra-trade-in-price-one-ui-85/",
      "publishedAt": "2026-05-09T20:14:47.000000Z"
    },
    {
      "index": 78,
      "headline": "\"China is Just Watching\": Ro Khanna on Why the Iran Conflict is a Gift to Beijing",
      "url": "https://www.bloomberg.com/news/videos/2026-05-09/ro-khanna-on-why-the-iran-conflict-is-a-gift-to-beijing-video",
      "publishedAt": "2026-05-09T16:45:17+00:00"
    },
    {
      "index": 79,
      "headline": "Schwab explains why a cheap-looking stock could be a trap",
      "url": "https://finance.yahoo.com/markets/stocks/articles/schwab-explains-why-cheap-looking-194700576.html",
      "publishedAt": "2026-05-09T19:47:00Z"
    },
    {
      "index": 80,
      "headline": "ABC accuses Trump administration of violating free speech rights",
      "url": "https://www.nbcnews.com/business/media/abc-accuses-trump-administration-violating-free-speech-rights-rcna344247",
      "publishedAt": "2026-05-08T17:26:29+00:00"
    },
    {
      "index": 81,
      "headline": "‘The risk of $5 gasoline can no longer be dismissed’ - Financial Times",
      "url": "https://www.ft.com/content/17ed835f-be7c-4961-afde-14d31baebfcc",
      "publishedAt": "2026-05-08T16:17:07Z"
    },
    {
      "index": 82,
      "headline": "Clean Harbors Q1 Earnings Call Highlights",
      "url": "https://finance.yahoo.com/markets/stocks/articles/clean-harbors-q1-earnings-call-200429890.html",
      "publishedAt": "2026-05-09T20:04:29Z"
    },
    {
      "index": 83,
      "headline": "China Summit Stays on Track Despite Iran Concerns",
      "url": "https://www.bloomberg.com/news/videos/2026-05-09/china-summit-stays-on-track-despite-iran-concerns-video",
      "publishedAt": "2026-05-09T16:56:17+00:00"
    },
    {
      "index": 84,
      "headline": "China’s Energy Imports Plunge as War Chokes Hormuz Shipments",
      "url": "https://www.bloomberg.com/news/articles/2026-05-09/china-s-energy-imports-plunge-as-war-chokes-hormuz-shipments",
      "publishedAt": "2026-05-09T04:33:32+00:00"
    },
    {
      "index": 85,
      "headline": "Cloudflare To Cut More Than 1,100 Jobs In Latest AI Layoff. Stock Falls. - Investor's Business Daily",
      "url": "https://www.investors.com/news/technology/cloudflare-stock-layoffs-ai-jobs/",
      "publishedAt": "2026-05-08T15:33:00Z"
    },
    {
      "index": 86,
      "headline": "Nvidia Stock Heads for Record as AI Push Expands - Barron's",
      "url": "https://www.barrons.com/articles/nvidia-stock-price-iren-ai-deal-bdfabcae",
      "publishedAt": "2026-05-08T15:12:00Z"
    },
    {
      "index": 87,
      "headline": "Jim Cramer on Meta: “I Think It’s Time to Stop Worrying and Start Buying”",
      "url": "https://finance.yahoo.com/markets/stocks/articles/jim-cramer-meta-think-time-184749430.html",
      "publishedAt": "2026-05-09T18:47:49Z"
    },
    {
      "index": 88,
      "headline": "DOJ probing trades in oil futures and prediction markets just ahead of major Iran war news",
      "url": "https://www.nbcnews.com/business/energy/doj-probes-oil-prediction-markets-iran-news-rcna344135",
      "publishedAt": "2026-05-07T21:56:36+00:00"
    },
    {
      "index": 89,
      "headline": "Jim Cramer Reviews the Earnings Report from Solstice Advanced Materials",
      "url": "https://finance.yahoo.com/markets/stocks/articles/jim-cramer-reviews-earnings-report-183643925.html",
      "publishedAt": "2026-05-09T18:36:43Z"
    },
    {
      "index": 90,
      "headline": "DOJ Probing Suspicious Oil Trades Tied To Iran War",
      "url": "https://www.bloomberg.com/news/videos/2026-05-09/doj-probing-suspicious-oil-trades-tied-to-iran-war-video",
      "publishedAt": "2026-05-09T16:36:41+00:00"
    },
    {
      "index": 91,
      "headline": "Apple, Intel Have Reached Preliminary Chip-Making Agreement - WSJ",
      "url": "https://www.wsj.com/tech/apple-intel-have-reached-preliminary-chip-making-agreement-69eb9370",
      "publishedAt": "2026-05-08T16:48:00Z"
    },
    {
      "index": 92,
      "headline": "Florida, Louisiana-Focused Insurer Safepoint Files for IPO",
      "url": "https://www.bloomberg.com/news/articles/2026-05-08/florida-and-louisiana-focused-insurer-safepoint-files-for-us-ipo",
      "publishedAt": "2026-05-08T22:27:41+00:00"
    },
    {
      "index": 93,
      "headline": "UK Moves Warship to Middle East for Potential Hormuz Mission",
      "url": "https://www.bloomberg.com/news/articles/2026-05-09/uk-moves-warship-to-middle-east-for-potential-hormuz-mission",
      "publishedAt": "2026-05-09T12:00:06+00:00"
    },
    {
      "index": 94,
      "headline": "White House Drug Czar Clarifies That Marijuana Is 'Still Illegal' Following Trump Administration's Rescheduling Move - Marijuana Moment",
      "url": "https://www.marijuanamoment.net/white-house-drug-czar-clarifies-that-marijuana-is-still-illegal-following-trump-administrations-rescheduling-move/",
      "publishedAt": "2026-05-08T14:17:36Z"
    },
    {
      "index": 95,
      "headline": "Apollo CEO warns there’s now a 35% chance of a major market shock amid AI-driven upheaval. How to stay afloat",
      "url": "https://finance.yahoo.com/markets/stocks/articles/apollo-ceo-warns-now-35-173000193.html",
      "publishedAt": "2026-05-09T17:30:00Z"
    },
    {
      "index": 96,
      "headline": "Jim Cramer Says “You Can’t Really Teach an Old Dog New Tricks Unless It’s a Datadog”",
      "url": "https://finance.yahoo.com/markets/stocks/articles/jim-cramer-says-t-really-183627769.html",
      "publishedAt": "2026-05-09T18:36:27Z"
    },
    {
      "index": 97,
      "headline": "Daniel Dae Kim Make Korean Culture Global in Docuseries",
      "url": "https://www.bloomberg.com/news/videos/2026-05-09/daniel-dae-kim-make-korean-culture-global-in-docuseries-video",
      "publishedAt": "2026-05-09T14:09:30+00:00"
    },
    {
      "index": 98,
      "headline": "China Vows to Advance Efforts to Defuse Local Government Debt",
      "url": "https://www.bloomberg.com/news/articles/2026-05-09/china-vows-to-advance-efforts-to-defuse-local-government-debt",
      "publishedAt": "2026-05-09T12:25:30+00:00"
    },
    {
      "index": 99,
      "headline": "US Adds 115,000 Jobs in April Despite Concerns Over Iran War",
      "url": "https://www.today.com/video/us-economy-remains-resilient-despite-the-war-in-iran-263045189589",
      "publishedAt": "2026-05-09T12:55:40+00:00"
    },
    {
      "index": 100,
      "headline": "Jim Cramer on Thermo Fisher: “I Think You Can Buy It at This Level”",
      "url": "https://finance.yahoo.com/markets/stocks/articles/jim-cramer-thermo-fisher-think-183650297.html",
      "publishedAt": "2026-05-09T18:36:50Z"
    },
    {
      "index": 101,
      "headline": "Winning the Degenerate Economy: Masters in Business with Howard Lindzon",
      "url": "https://www.bloomberg.com/news/videos/2026-05-08/winning-the-degenerate-economy-howard-lindzon-video",
      "publishedAt": "2026-05-08T21:20:18+00:00"
    }
  ]
}